LICENSE
MANIFEST.in
README.md
requirements.txt
setup.py
test-requirements.txt
version.py
moksha_monitor_exporter/__init__.py
moksha_monitor_exporter/moksha_monitor_exporter.py
moksha_monitor_exporter.egg-info/PKG-INFO
moksha_monitor_exporter.egg-info/SOURCES.txt
moksha_monitor_exporter.egg-info/dependency_links.txt
moksha_monitor_exporter.egg-info/not-zip-safe
moksha_monitor_exporter.egg-info/requires.txt
moksha_monitor_exporter.egg-info/top_level.txt
tests/test_server.py